setup.cfg
setup.py
libedooon/__init__.py
libedooon/activity.py
libedooon/constant.py
libedooon/exception.py
libedooon/user.py
libedooon.egg-info/PKG-INFO
libedooon.egg-info/SOURCES.txt
libedooon.egg-info/dependency_links.txt
libedooon.egg-info/requires.txt
libedooon.egg-info/top_level.txt