Metadata-Version: 1.1
Name: libedooon
Version: 0.2.3
Summary: A Python wrap for Edooon RESTful APIs.
Home-page: https://github.com/yangl1996/libedooon
Author: Lei Yang
Author-email: yltt1234512@gmail.com
License: MIT License
Keywords: api,library
Platform: UNKNOWN
Classifier: Development Status :: 4 - Beta
Classifier: Intended Audience :: Developers
Classifier: Intended Audience :: End Users/Desktop
Classifier: License :: OSI Approved :: MIT License
Classifier: Programming Language :: Python
Classifier: Programming Language :: Python :: 3
Classifier: Programming Language :: Python :: 3 :: Only
Classifier: Programming Language :: Python :: 3.5
Classifier: Topic :: Software Development :: Libraries
Classifier: Topic :: Scientific/Engineering :: GIS
